ubuntu_package_buildinfo/__init__.py
ubuntu_package_buildinfo/cli.py
ubuntu_package_buildinfo/find_source_package_name.py
ubuntu_package_buildinfo/find_sources_packages_without_buildinfo.py
ubuntu_package_buildinfo/packages_in_main_manifest.py
ubuntu_package_buildinfo/published_source_packages_in_archive.py
ubuntu_package_buildinfo/ubuntu_package_download_deb.py
ubuntu_package_buildinfo-0.0.10.dist-info/AUTHORS.rst
ubuntu_package_buildinfo-0.0.10.dist-info/LICENSE
ubuntu_package_buildinfo-0.0.10.dist-info/METADATA
ubuntu_package_buildinfo-0.0.10.dist-info/WHEEL
ubuntu_package_buildinfo-0.0.10.dist-info/entry_points.txt
ubuntu_package_buildinfo-0.0.10.dist-info/top_level.txt
ubuntu_package_buildinfo-0.0.10.dist-info/RECORD
