Metadata-Version: 2.1
Name: ubuntu-package-buildinfo
Version: 0.0.10
Summary: Tool to retrieve Ubuntu Package Buildinfo
Home-page: https://github.com/canonical/ubuntu-package-buildinfo
Author: Phil Roche
Author-email: phil.roche@canonical.com
License: GNU General Public License v3
Keywords: ubuntu-package-buildinfo
Classifier: Development Status :: 2 - Pre-Alpha
Classifier: Intended Audience :: Developers
Classifier: License :: OSI Approved :: GNU General Public License v3 (GPLv3)
Classifier: Natural Language :: English
Classifier: Programming Language :: Python :: 3
Classifier: Programming Language :: Python :: 3.6
Classifier: Programming Language :: Python :: 3.7
Classifier: Programming Language :: Python :: 3.8
Requires-Python: >=3.6
License-File: LICENSE
License-File: AUTHORS.rst
Requires-Dist: Click (>=7.0)
Requires-Dist: launchpadlib
